cao/__init__.py
cao/__main__.py
cao/cli.py
cao/engine.py
cao/registry.py
cao/sources/__init__.py
cao/sources/base.py
cao/sources/geospatial/__init__.py
cao/sources/geospatial/geospatial_csv_source.py
cao/sources/geospatial/geospatial_source.py
cao/sources/image/__init__.py
cao/sources/image/image_open_source.py
cao/targets/__init__.py
cao/targets/base.py
cao/targets/geospatial/__init__.py
cao/targets/geospatial/geospatial_csv_target.py
cao/targets/geospatial/geospatial_target.py
cao/targets/image/__init__.py
cao/targets/image/image_save_target.py
cao/targets/text/__init__.py
cao/targets/text/txt_target.py
convert_offline-0.1.2.dist-info/licenses/LICENSE
convert_offline-0.1.2.dist-info/METADATA
convert_offline-0.1.2.dist-info/WHEEL
convert_offline-0.1.2.dist-info/entry_points.txt
convert_offline-0.1.2.dist-info/top_level.txt
convert_offline-0.1.2.dist-info/RECORD
