Metadata-Version: 2.4
Name: convert-offline
Version: 0.1.2
Summary: Convert Anything Offline — a modular CLI tool for file format conversion.
Author: Jack McNulty
Author-email: jackmcnulty76@gmail.com
License: MIT
Classifier: Programming Language :: Python :: 3
Classifier: License :: OSI Approved :: MIT License
Classifier: Operating System :: OS Independent
Requires-Python: >=3.8
License-File: LICENSE
Requires-Dist: click
Requires-Dist: Pillow
Requires-Dist: geopandas
Requires-Dist: pandas
Requires-Dist: shapely
Requires-Dist: pyarrow
Requires-Dist: fiona
Dynamic: author
Dynamic: author-email
Dynamic: classifier
Dynamic: description
Dynamic: description-content-type
Dynamic: license
Dynamic: license-file
Dynamic: requires-dist
Dynamic: requires-python
Dynamic: summary
